nonebot_plugin_flo_luck/__init__.py
nonebot_plugin_flo_luck/database.py
nonebot_plugin_flo_luck/helper_functions.py
nonebot_plugin_flo_luck-0.2.1.dist-info/LICENSE
nonebot_plugin_flo_luck-0.2.1.dist-info/METADATA
nonebot_plugin_flo_luck-0.2.1.dist-info/WHEEL
nonebot_plugin_flo_luck-0.2.1.dist-info/RECORD
