Metadata-Version: 2.1
Name: nonebot-plugin-flo-luck
Version: 0.2.1
Summary: nonebot plugin for today's luck.
License: MIT
Author: florenz
Author-email: florenz@tju.edu.cn
Requires-Python: >=3.9,<4.0
Classifier: License :: OSI Approved :: MIT License
Classifier: Programming Language :: Python :: 3
Classifier: Programming Language :: Python :: 3.9
Classifier: Programming Language :: Python :: 3.10
Classifier: Programming Language :: Python :: 3.11
Classifier: Programming Language :: Python :: 3.12
Classifier: Programming Language :: Python :: 3.13
Requires-Dist: nonebot-plugin-alconna (>=0.54.1)
Requires-Dist: nonebot-plugin-localstore (>=0.7.2)
Requires-Dist: nonebot-plugin-uninfo (>=0.6.2)
Requires-Dist: nonebot2 (>=2.4.0)
